nexusai/__init__.py
nexusai/client.py
nexusai/exceptions.py
nexusai_py-5.0.4.dist-info/licenses/LICENSE
nexusai_py-5.0.4.dist-info/METADATA
nexusai_py-5.0.4.dist-info/WHEEL
nexusai_py-5.0.4.dist-info/top_level.txt
nexusai_py-5.0.4.dist-info/RECORD
