Metadata-Version: 2.4
Name: nexusai-py
Version: 5.0.4
Summary: A comprehensive Python wrapper for the Nexus AI API
Home-page: https://nexus.drexus.xyz
Author: Nexus API
Author-email: Nexus API <drezus.nexus@gmail.com>
License: MIT
Project-URL: Homepage, https://nexus.drexus.xyz
Project-URL: Documentation, https://nexus.drexus.xyz/docs
Project-URL: Discord, https://discord.gg/qdgkMkQbnt
Keywords: ai,api,nexus,image-generation,text-generation,gemini,gpt-4,akinator
Classifier: Development Status :: 5 - Production/Stable
Classifier: Intended Audience :: Developers
Classifier: License :: OSI Approved :: MIT License
Classifier: Programming Language :: Python :: 3
Requires-Python: >=3.7
License-File: LICENSE
Requires-Dist: requests>=2.25.0
Provides-Extra: dev
Requires-Dist: pytest>=6.0; extra == "dev"
Requires-Dist: black>=21.0; extra == "dev"
Provides-Extra: examples
Requires-Dist: Pillow>=8.0; extra == "examples"
Dynamic: author
Dynamic: home-page
Dynamic: license-file
Dynamic: requires-python
